TelegramBotsCallbackData
