Metadata-Version: 2.1
Name: TelegramBotsCallbackData
Version: 1.0.2
Summary: This is a library for storing a lot of information in callback data
Home-page: https://github.com/Wintreist/TelegramBotsCallbackData
Author: Wintreist
Author-email: wintreist1811@gmail.com
Project-URL: GitHub, https://github.com/Wintreist
Keywords: Telegram Callback
Requires-Python: >=3.6
